{
    "header": {
        "version": 2,
        "id": "71-00-51-400-803-A",
        "owner": "A321Neo",
        "title": "71-00-51-400-803-A",
        "tags": ""
    },
    "metadataObject": [
        {
            "id": "1",
            "name": "Prev",
            "img": "",
            "content": "Prev.html",
            "timeRange": [
                0.0,
                99.0
            ],
            "bbox": [
                [
                    0.0,
                    [
                        0.06499998271465302,
                        0.54666668176651
                    ],
                    [
                        0.012499979697167873,
                        0.45333331823349
                    ]
                ],
                [
                    99.0,
                    [
                        0.06499998271465302,
                        0.54666668176651
                    ],
                    [
                        0.012499979697167873,
                        0.45333331823349
                    ]
                ]
            ]
        },
        {
            "id": "2",
            "name": "Next",
            "img": "",
            "content": "Next.html",
            "timeRange": [
                0.0,
                99.0
            ],
            "bbox": [
                [
                    0.0,
                    [
                        0.9350000619888306,
                        0.45333331823349
                    ],
                    [
                        0.9875000715255737,
                        0.54666668176651
                    ]
                ],
                [
                    99.0,
                    [
                        0.9350000619888306,
                        0.45333331823349
                    ],
                    [
                        0.9875000715255737,
                        0.54666668176651
                    ]
                ]
            ]
        },
        {
            "id": "3",
            "name": "Pressure hose (62)",
            "img": "",
            "content": "Pressure hose (62).html",
            "timeRange": [
                0.0,
                99.0
            ],
            "bbox": [
                [
                    0.0,
                    [
                        0.6771644353866577,
                        0.4608041048049927
                    ],
                    [
                        0.8419140577316284,
                        0.51413893699646
                    ]
                ],
                [
                    99.0,
                    [
                        0.6771644353866577,
                        0.4608041048049927
                    ],
                    [
                        0.8419140577316284,
                        0.51413893699646
                    ]
                ]
            ]
        },
        {
            "id": "4",
            "name": "Bolt(107)",
            "img": "",
            "content": "Bolt(107).html",
            "timeRange": [
                0.0,
                99.0
            ],
            "bbox": [
                [
                    0.0,
                    [
                        0.4396405816078186,
                        0.5693283081054688
                    ],
                    [
                        0.5646723508834839,
                        0.6242222189903259
                    ]
                ],
                [
                    99.0,
                    [
                        0.4396405816078186,
                        0.5693283081054688
                    ],
                    [
                        0.5646723508834839,
                        0.6242222189903259
                    ]
                ]
            ]
        }
    ]
}